calc/__init__.py
calc/calculadora.py
msm_calc-1.2.dist-info/LICENSE
msm_calc-1.2.dist-info/METADATA
msm_calc-1.2.dist-info/WHEEL
msm_calc-1.2.dist-info/top_level.txt
msm_calc-1.2.dist-info/RECORD
